uart-rtl-core/rtl/uart_rx.v
// =============================================================================
// uart_rx.v
// UART Receiver (8 data bits, no parity, 1 stop bit -- "8N1")
//
// Watches the rx line for a falling edge (start bit), confirms it at the
// bit's midpoint to reject glitches, then samples each of the 8 data bits
// at its midpoint using the 16x baud_tick for accurate alignment even if
// the incoming edge is not perfectly synchronized to our clock.
// =============================================================================

`timescale 1ns/1ps

module uart_rx (
    input  wire       clk,
    input  wire       rst_n,
    input  wire       baud_tick,   // 16x baud rate tick from baud_gen
    input  wire       rx,          // serial input line (idles high)
    output reg  [7:0] rx_data,     // last byte received
    output reg        rx_valid     // 1 clk-cycle pulse when rx_data is new
);

    localparam IDLE      = 2'd0,
               START_BIT = 2'd1,
               DATA_BITS = 2'd2,
               STOP_BIT  = 2'd3;

    reg [1:0] state;
    reg [3:0] tick_cnt;
    reg [2:0] bit_idx;
    reg [7:0] shift_reg;

    // 2-flip-flop synchronizer: rx is an asynchronous external input,
    // so it must be synchronized into the clk domain before use to
    // avoid metastability.
    reg rx_sync0, rx_sync1;

    always @(posedge clk or negedge rst_n) begin
        if (!rst_n) begin
            rx_sync0 <= 1'b1;
            rx_sync1 <= 1'b1;
        end else begin
            rx_sync0 <= rx;
            rx_sync1 <= rx_sync0;
        end
    end

    always @(posedge clk or negedge rst_n) begin
        if (!rst_n) begin
            state     <= IDLE;
            tick_cnt  <= 4'd0;
            bit_idx   <= 3'd0;
            shift_reg <= 8'd0;
            rx_data   <= 8'd0;
            rx_valid  <= 1'b0;
        end else begin
            rx_valid <= 1'b0;   // default: rx_valid is a single-cycle pulse

            case (state)
                // Wait for the line to fall low (candidate start bit).
                IDLE: begin
                    tick_cnt <= 4'd0;
                    if (rx_sync1 == 1'b0) begin
                        state <= START_BIT;
                    end
                end

                // Confirm the start bit at its midpoint (8 of 16 ticks in).
                // This rejects short glitches that are not a real start bit.
                START_BIT: begin
                    if (baud_tick) begin
                        if (tick_cnt == 4'd7) begin
                            if (rx_sync1 == 1'b0) begin
                                tick_cnt <= 4'd0;
                                bit_idx  <= 3'd0;
                                state    <= DATA_BITS;
                            end else begin
                                state <= IDLE;  // false start, go back to waiting
                            end
                        end else begin
                            tick_cnt <= tick_cnt + 4'd1;
                        end
                    end
                end

                // Sample each data bit at its midpoint, LSB first.
                DATA_BITS: begin
                    if (baud_tick) begin
                        if (tick_cnt == 4'd15) begin
                            tick_cnt <= 4'd0;
                            shift_reg[bit_idx] <= rx_sync1;
                            if (bit_idx == 3'd7) begin
                                state <= STOP_BIT;
                            end else begin
                                bit_idx <= bit_idx + 3'd1;
                            end
                        end else begin
                            tick_cnt <= tick_cnt + 4'd1;
                        end
                    end
                end

                // Land at the midpoint of the stop bit, latch the received
                // byte and pulse rx_valid, then return to idle.
                STOP_BIT: begin
                    if (baud_tick) begin
                        if (tick_cnt == 4'd15) begin
                            tick_cnt <= 4'd0;
                            rx_data  <= shift_reg;
                            rx_valid <= 1'b1;
                            state    <= IDLE;
                        end else begin
                            tick_cnt <= tick_cnt + 4'd1;
                        end
                    end
                end

                default: state <= IDLE;
            endcase
        end
    end

endmodule

uart-rtl-core/rtl/uart_tx.v
// =============================================================================
// uart_tx.v
// UART Transmitter (8 data bits, no parity, 1 stop bit -- "8N1")
//
// Serializes tx_data onto the tx line one bit at a time, framed as:
//   [ start bit (0) ][ 8 data bits, LSB first ][ stop bit (1) ]
// Each bit is held for 16 baud_tick pulses (16x oversampled bit period).
// =============================================================================

`timescale 1ns/1ps

module uart_tx (
    input  wire       clk,
    input  wire       rst_n,
    input  wire       baud_tick,   // 16x baud rate tick from baud_gen
    input  wire       tx_start,    // pulse high for >=1 clk to begin a frame
    input  wire [7:0] tx_data,     // byte to transmit, sampled when tx_start fires
    output reg        tx,          // serial output line (idles high)
    output reg        tx_busy      // high while a frame is in progress
);

    localparam IDLE      = 2'd0,
               START_BIT = 2'd1,
               DATA_BITS = 2'd2,
               STOP_BIT  = 2'd3;

    reg [1:0] state;
    reg [3:0] tick_cnt;   // counts 0-15 within the current bit period
    reg [2:0] bit_idx;    // index of the data bit currently being sent (0-7)
    reg [7:0] shift_reg;  // holds the byte being shifted out

    always @(posedge clk or negedge rst_n) begin
        if (!rst_n) begin
            state     <= IDLE;
            tx        <= 1'b1;   // idle line level is high
            tx_busy   <= 1'b0;
            tick_cnt  <= 4'd0;
            bit_idx   <= 3'd0;
            shift_reg <= 8'd0;
        end else begin
            case (state)
                // Wait for a request to send a byte.
                IDLE: begin
                    tx <= 1'b1;
                    if (tx_start) begin
                        shift_reg <= tx_data;
                        tx_busy   <= 1'b1;
                        tick_cnt  <= 4'd0;
                        state     <= START_BIT;
                    end else begin
                        tx_busy <= 1'b0;
                    end
                end

                // Drive the line low for one full bit period.
                START_BIT: begin
                    tx <= 1'b0;
                    if (baud_tick) begin
                        if (tick_cnt == 4'd15) begin
                            tick_cnt <= 4'd0;
                            bit_idx  <= 3'd0;
                            state    <= DATA_BITS;
                        end else begin
                            tick_cnt <= tick_cnt + 4'd1;
                        end
                    end
                end

                // Shift out 8 data bits, LSB first.
                DATA_BITS: begin
                    tx <= shift_reg[bit_idx];
                    if (baud_tick) begin
                        if (tick_cnt == 4'd15) begin
                            tick_cnt <= 4'd0;
                            if (bit_idx == 3'd7) begin
                                state <= STOP_BIT;
                            end else begin
                                bit_idx <= bit_idx + 3'd1;
                            end
                        end else begin
                            tick_cnt <= tick_cnt + 4'd1;
                        end
                    end
                end

                // Drive the line high for one full bit period, then return to idle.
                STOP_BIT: begin
                    tx <= 1'b1;
                    if (baud_tick) begin
                        if (tick_cnt == 4'd15) begin
                            tick_cnt <= 4'd0;
                            tx_busy  <= 1'b0;
                            state    <= IDLE;
                        end else begin
                            tick_cnt <= tick_cnt + 4'd1;
                        end
                    end
                end

                default: state <= IDLE;
            endcase
        end
    end

endmodule

uart-rtl-core/rtl/baud_gen.v
// =============================================================================
// baud_gen.v
// Baud-rate tick generator.
//
// Divides the system clock down to a tick that pulses at 16x the target
// baud rate. Both uart_tx and uart_rx use this 16x tick for internal timing:
// uart_tx counts 16 ticks per bit period, and uart_rx uses the same 16x
// resolution to sample each incoming bit at its midpoint.
// =============================================================================

`timescale 1ns/1ps

module baud_gen #(
    parameter CLK_FREQ  = 1_843_200,  // system clock frequency, Hz
    parameter BAUD_RATE = 9600        // desired UART baud rate
)(
    input  wire clk,
    input  wire rst_n,
    output reg  tick        // 1 clk-cycle-wide pulse at 16x BAUD_RATE
);

    // Number of system clock cycles per 16x tick.
    // Example: 1,843,200 Hz / (9600 * 16) = 12 clocks per tick.
    localparam integer DIVISOR = CLK_FREQ / (BAUD_RATE * 16);

    reg [15:0] count;

    always @(posedge clk or negedge rst_n) begin
        if (!rst_n) begin
            count <= 16'd0;
            tick  <= 1'b0;
        end else if (count == DIVISOR - 1) begin
            count <= 16'd0;
            tick  <= 1'b1;
        end else begin
            count <= count + 16'd1;
            tick  <= 1'b0;
        end
    end

endmodule

uart-rtl-core/rtl/uart_top.v
// =============================================================================
// uart_top.v
// Top-level UART core: integrates the baud generator, transmitter and
// receiver behind a single set of ports.
//
// tx and rx share one internal serial line ("serial_line") so the core is a
// self-contained loopback UART: whatever byte is transmitted comes back out
// on rx_data. This makes the design fully self-verifiable in simulation
// with no external testbench-side serial modeling required. In a real
// system, uart_tx's output and uart_rx's input would instead connect to the
// TX/RX pins of an external UART device (see "Future Improvements" in the
// README for how to split this into independent TX/RX pins).
// =============================================================================

`timescale 1ns/1ps

module uart_top #(
    parameter CLK_FREQ  = 1_843_200,
    parameter BAUD_RATE = 9600
)(
    input  wire       clk,
    input  wire       rst_n,

    // transmit side
    input  wire       tx_start,
    input  wire [7:0] tx_data,
    output wire        tx_busy,

    // receive side
    output wire [7:0] rx_data,
    output wire       rx_valid,

    // observable serial line (tx drives it, rx listens to it)
    output wire       serial_line
);

    wire baud_tick;

    baud_gen #(
        .CLK_FREQ (CLK_FREQ),
        .BAUD_RATE(BAUD_RATE)
    ) u_baud_gen (
        .clk  (clk),
        .rst_n(rst_n),
        .tick (baud_tick)
    );

    uart_tx u_uart_tx (
        .clk      (clk),
        .rst_n    (rst_n),
        .baud_tick(baud_tick),
        .tx_start (tx_start),
        .tx_data  (tx_data),
        .tx       (serial_line),
        .tx_busy  (tx_busy)
    );

    uart_rx u_uart_rx (
        .clk      (clk),
        .rst_n    (rst_n),
        .baud_tick(baud_tick),
        .rx       (serial_line),
        .rx_data  (rx_data),
        .rx_valid (rx_valid)
    );

endmodule

uart-rtl-core/tb/tb_uart_top.v
// =============================================================================
// tb_uart_top.v
// Self-checking testbench for uart_top.
//
// Drives tx_start/tx_data, waits for the loopback rx_valid pulse, and
// compares rx_data against what was sent. Prints a PASS/FAIL line per test
// and a final summary, then calls $finish automatically.
// =============================================================================

`timescale 1ns/1ps

module tb_uart_top;

    localparam CLK_FREQ   = 1_843_200;
    localparam BAUD_RATE  = 9600;
    localparam CLK_PERIOD = 1_000_000_000 / CLK_FREQ;   // ns, ~542 ns

    reg        clk;
    reg        rst_n;
    reg        tx_start;
    reg  [7:0] tx_data;
    wire       tx_busy;
    wire [7:0] rx_data;
    wire       rx_valid;
    wire       serial_line;

    integer pass_count;
    integer fail_count;
    integer test_num;

    uart_top #(
        .CLK_FREQ (CLK_FREQ),
        .BAUD_RATE(BAUD_RATE)
    ) dut (
        .clk        (clk),
        .rst_n      (rst_n),
        .tx_start   (tx_start),
        .tx_data    (tx_data),
        .tx_busy    (tx_busy),
        .rx_data    (rx_data),
        .rx_valid   (rx_valid),
        .serial_line(serial_line)
    );

    // clock generation
    initial clk = 1'b0;
    always #(CLK_PERIOD/2) clk = ~clk;

    // waveform dump
    initial begin
        $dumpfile("simulation.vcd");
        $dumpvars(0, tb_uart_top);
    end

    // Sends one byte and checks it comes back correctly via loopback.
    task send_and_check(input [7:0] data, input [23*8:0] label);
        begin
            test_num = test_num + 1;
            @(posedge clk);
            tx_start <= 1'b1;
            tx_data  <= data;
            @(posedge clk);
            tx_start <= 1'b0;

            fork : wait_block
                begin
                    wait (rx_valid == 1'b1);
                    disable wait_block;
                end
                begin
                    #(CLK_PERIOD * 20000);   // generous timeout safety net
                    disable wait_block;
                end
            join

            if (rx_valid && rx_data == data) begin
                $display("Test %0d: %-24s PASS  (sent=0x%02h received=0x%02h)",
                          test_num, label, data, rx_data);
                pass_count = pass_count + 1;
            end else begin
                $display("Test %0d: %-24s FAIL  (sent=0x%02h received=0x%02h rx_valid=%b)",
                          test_num, label, data, rx_data, rx_valid);
                fail_count = fail_count + 1;
            end

            // uart_rx raises rx_valid at the midpoint of the stop bit (for
            // fast turnaround), which is *before* uart_tx finishes driving
            // the full stop-bit period and clears tx_busy. Wait for tx_busy
            // to actually clear before starting the next frame, otherwise a
            // new tx_start would arrive while the core is still busy and be
            // correctly-but-inconveniently ignored.
            if (tx_busy) begin
                wait (tx_busy == 1'b0);
            end
            @(posedge clk);
        end
    endtask

    initial begin
        pass_count = 0;
        fail_count = 0;
        test_num   = 0;
        tx_start   = 1'b0;
        tx_data    = 8'h00;
        rst_n      = 1'b0;

        $display("========================================");
        $display("        UART SIMULATION");
        $display("========================================");

        // Test 1: reset drives the core to a known idle state
        repeat (5) @(posedge clk);
        test_num = test_num + 1;
        if (tx_busy == 1'b0 && serial_line == 1'b1) begin
            $display("Test %0d: %-24s PASS", test_num, "Reset");
            pass_count = pass_count + 1;
        end else begin
            $display("Test %0d: %-24s FAIL", test_num, "Reset");
            fail_count = fail_count + 1;
        end
        rst_n = 1'b1;
        repeat (5) @(posedge clk);

        // Tests 2-3: basic single-character transmission
        send_and_check(8'h41, "Transmit 'A'");
        send_and_check(8'h42, "Transmit 'B'");

        // Test 4: boundary value - all zeros
        send_and_check(8'h00, "Transmit 0x00");

        // Test 5: boundary value - all ones
        send_and_check(8'hFF, "Transmit 0xFF");

        // Tests 6-7: back-to-back multiple bytes
        send_and_check(8'h48, "Multi-byte 'H'");
        send_and_check(8'h49, "Multi-byte 'I'");

        // Test 8: edge case - a second tx_start arriving while the core is
        // already busy transmitting must be ignored (frame must not restart
        // or corrupt mid-transmission).
        test_num = test_num + 1;
        @(posedge clk);
        tx_start <= 1'b1;
        tx_data  <= 8'h58;          // 'X'
        @(posedge clk);
        tx_start <= 1'b1;           // still asserted
        tx_data  <= 8'h59;          // 'Y' - must be ignored, core is now busy
        @(posedge clk);
        tx_start <= 1'b0;

        wait (rx_valid == 1'b1);
        if (rx_data == 8'h58) begin
            $display("Test %0d: %-24s PASS  (busy correctly ignored new tx_start)",
                      test_num, "Invalid/edge case");
            pass_count = pass_count + 1;
        end else begin
            $display("Test %0d: %-24s FAIL  (unexpected byte 0x%02h)",
                      test_num, "Invalid/edge case", rx_data);
            fail_count = fail_count + 1;
        end

        repeat (20) @(posedge clk);

        $display("----------------------------------------");
        if (fail_count == 0) begin
            $display("ALL %0d TESTS PASSED", pass_count);
        end else begin
            $display("%0d PASSED, %0d FAILED", pass_count, fail_count);
        end
        $display("----------------------------------------");

        $finish;
    end

endmodule

uart-rtl-core/simulation/simulation.vcd
$date
	Sun Sep 27 05:20:10 2026
$end
$version
	Icarus Verilog
$end
$timescale
	1ps
$end
$scope module tb_uart_top $end
$var wire 1 ! tx_busy $end
$var wire 1 " serial_line $end
$var wire 1 # rx_valid $end
$var wire 8 $ rx_data [7:0] $end
$var parameter 32 % BAUD_RATE $end
$var parameter 32 & CLK_FREQ $end
$var parameter 32 ' CLK_PERIOD $end
$var reg 1 ( clk $end
$var reg 1 ) rst_n $end
$var reg 8 * tx_data [7:0] $end
$var reg 1 + tx_start $end
$var integer 32 , fail_count [31:0] $end
$var integer 32 - pass_count [31:0] $end
$var integer 32 . test_num [31:0] $end
$scope module dut $end
$var wire 1 ( clk $end
$var wire 1 ) rst_n $end
$var wire 8 / tx_data [7:0] $end
$var wire 1 + tx_start $end
$var wire 1 ! tx_busy $end
$var wire 1 " serial_line $end
$var wire 1 # rx_valid $end
$var wire 8 0 rx_data [7:0] $end
$var wire 1 1 baud_tick $end
$var parameter 32 2 BAUD_RATE $end
$var parameter 32 3 CLK_FREQ $end
$scope module u_baud_gen $end
$var wire 1 ( clk $end
$var wire 1 ) rst_n $end
$var parameter 32 4 BAUD_RATE $end
$var parameter 32 5 CLK_FREQ $end
$var parameter 32 6 DIVISOR $end
$var reg 16 7 count [15:0] $end
$var reg 1 1 tick $end
$upscope $end
$scope module u_uart_rx $end
$var wire 1 1 baud_tick $end
$var wire 1 ( clk $end
$var wire 1 ) rst_n $end
$var wire 1 " rx $end
$var parameter 2 8 DATA_BITS $end
$var parameter 2 9 IDLE $end
$var parameter 2 : START_BIT $end
$var parameter 2 ; STOP_BIT $end
$var reg 3 < bit_idx [2:0] $end
$var reg 8 = rx_data [7:0] $end
$var reg 1 > rx_sync0 $end
$var reg 1 ? rx_sync1 $end
$var reg 1 # rx_valid $end
$var reg 8 @ shift_reg [7:0] $end
$var reg 2 A state [1:0] $end
$var reg 4 B tick_cnt [3:0] $end
$upscope $end
$scope module u_uart_tx $end
$var wire 1 1 baud_tick $end
$var wire 1 ( clk $end
$var wire 1 ) rst_n $end
$var wire 8 C tx_data [7:0] $end
$var wire 1 + tx_start $end
$var parameter 2 D DATA_BITS $end
$var parameter 2 E IDLE $end
$var parameter 2 F START_BIT $end
$var parameter 2 G STOP_BIT $end
$var reg 3 H bit_idx [2:0] $end
$var reg 8 I shift_reg [7:0] $end
$var reg 2 J state [1:0] $end
$var reg 4 K tick_cnt [3:0] $end
$var reg 1 " tx $end
$var reg 1 ! tx_busy $end
$upscope $end
$upscope $end
$scope task send_and_check $end
$var reg 8 L data [7:0] $end
$var reg 185 M label [184:0] $end
$scope fork wait_block $end
$upscope $end
$upscope $end
$upscope $end
$enddefinitions $end
$comment Show the parameter values. $end
$dumpall
b11 G
b1 F
b0 E
b10 D
b11 ;
b1 :
b0 9
b10 8
b1100 6
b111000010000000000000 5
b10010110000000 4
b111000010000000000000 3
b10010110000000 2
b1000011110 '
b111000010000000000000 &
b10010110000000 %
$end
#0
$dumpvars
bx M
bx L
b0 K
b0 J
b0 I
b0 H
b0 C
b0 B
b0 A
b0 @
1?
1>
b0 =
b0 <
b0 7
01
b0 0
b0 /
b0 .
b0 -
b0 ,
0+
b0 *
0)
0(
b0 $
0#
1"
0!
$end
#271000
1(
#542000
0(
#813000
1(
#1084000
0(
#1355000
1(
#1626000
0(
#1897000
1(
#2168000
0(
#2439000
b1 7
1)
b1 -
b1 .
1(
#2710000
0(
#2981000
b10 7
1(
#3252000
0(
#3523000
b11 7
1(
#3794000
0(
#4065000
b100 7
1(
#4336000
0(
#4607000
b101 7
1(
#4878000
0(
#5149000
b110 7
b10 .
b10101000111001001100001011011100111001101101101011010010111010000100000001001110100000100100111 M
b1000001 L
1(
#5420000
0(
#5691000
b111 7
b1000001 *
b1000001 /
b1000001 C
1+
1(
#5962000
0(
#6233000
b1000 7
b1 J
1!
b1000001 I
0+
1(
#6504000
0(
#6775000
0"
b1001 7
1(
#7046000
0(
#7317000
b1010 7
0>
1(
#7588000
0(
#7859000
0?
b1011 7
1(
#8130000
0(
#8401000
11
b0 7
b1 A
1(
#8672000
0(
#8943000
b1 B
b1 K
01
b1 7
1(
#9214000
0(
#9485000
b10 7
1(
#9756000
0(
#10027000
b11 7
1(
#10298000
0(
#10569000
b100 7
1(
#10840000
0(
#11111000
b101 7
1(
#11382000
0(
#11653000
b110 7
1(
#11924000
0(
#12195000
b111 7
1(
#12466000
0(
#12737000
b1000 7
1(
#13008000
0(
#13279000
b1001 7
1(
#13550000
0(
#13821000
b1010 7
1(
#14092000
0(
#14363000
b1011 7
1(
#14634000
0(
#14905000
11
b0 7
1(
#15176000
0(
#15447000
b10 B
b10 K
01
b1 7
1(
#15718000
0(
#15989000
b10 7
1(
#16260000
0(
#16531000
b11 7
1(
#16802000
0(
#17073000
b100 7
1(
#17344000
0(
#17615000
b101 7
1(
#17886000
0(
#18157000
b110 7
1(
#18428000
0(
#18699000
b111 7
1(
#18970000
0(
#19241000
b1000 7
1(
#19512000
0(
#19783000
b1001 7
1(
#20054000
0(
#20325000
b1010 7
1(
#20596000
0(
#20867000
b1011 7
1(
#21138000
0(
#21409000
11
b0 7
1(
#21680000
0(
#21951000
b11 B
b11 K
01
b1 7
1(
#22222000
0(
#22493000
b10 7
1(
#22764000
0(
#23035000
b11 7
1(
#23306000
0(
#23577000
b100 7
1(
#23848000
0(
#24119000
b101 7
1(
#24390000
0(
#24661000
b110 7
1(
#24932000
0(
#25203000
b111 7
1(
#25474000
0(
#25745000
b1000 7
1(
#26016000
0(
#26287000
b1001 7
1(
#26558000
0(
#26829000
b1010 7
1(
#27100000
0(
#27371000
b1011 7
1(
#27642000
0(
#27913000
11
b0 7
1(
#28184000
0(
#28455000
b100 B
b100 K
01
b1 7
1(
#28726000
0(
#28997000
b10 7
1(
#29268000
0(
#29539000
b11 7
1(
#29810000
0(
#30081000
b100 7
1(
#30352000
0(
#30623000
b101 7
1(
#30894000
0(
#31165000
b110 7
1(
#31436000
0(
#31707000
b111 7
1(
#31978000
0(
#32249000
b1000 7
1(
#32520000
0(
#32791000
b1001 7
1(
#33062000
0(
#33333000
b1010 7
1(
#33604000
0(
#33875000
b1011 7
1(
#34146000
0(
#34417000
11
b0 7
1(
#34688000
0(
#34959000
b101 B
b101 K
01
b1 7
1(
#35230000
0(
#35501000
b10 7
1(
#35772000
0(
#36043000
b11 7
1(
#36314000
0(
#36585000
b100 7
1(
#36856000
0(
#37127000
b101 7
1(
#37398000
0(
#37669000
b110 7
1(
#37940000
0(
#38211000
b111 7
1(
#38482000
0(
#38753000
b1000 7
1(
#39024000
0(
#39295000
b1001 7
1(
#39566000
0(
#39837000
b1010 7
1(
#40108000
0(
#40379000
b1011 7
1(
#40650000
0(
#40921000
11
b0 7
1(
#41192000
0(
#41463000
b110 B
b110 K
01
b1 7
1(
#41734000
0(
#42005000
b10 7
1(
#42276000
0(
#42547000
b11 7
1(
#42818000
0(
#43089000
b100 7
1(
#43360000
0(
#43631000
b101 7
1(
#43902000
0(
#44173000
b110 7
1(
#44444000
0(
#44715000
b111 7
1(
#44986000
0(
#45257000
b1000 7
1(
#45528000
0(
#45799000
b1001 7
1(
#46070000
0(
#46341000
b1010 7
1(
#46612000
0(
#46883000
b1011 7
1(
#47154000
0(
#47425000
11
b0 7
1(
#47696000
0(
#47967000
b111 B
b111 K
01
b1 7
1(
#48238000
0(
#48509000
b10 7
1(
#48780000
0(
#49051000
b11 7
1(
#49322000
0(
#49593000
b100 7
1(
#49864000
0(
#50135000
b101 7
1(
#50406000
0(
#50677000
b110 7
1(
#50948000
0(
#51219000
b111 7
1(
#51490000
0(
#51761000
b1000 7
1(
#52032000
0(
#52303000
b1001 7
1(
#52574000
0(
#52845000
b1010 7
1(
#53116000
0(
#53387000
b1011 7
1(
#53658000
0(
#53929000
11
b0 7
1(
#54200000
0(
#54471000
b10 A
b0 B
b1000 K
01
b1 7
1(
#54742000
0(
#55013000
b10 7
1(
#55284000
0(
#55555000
b11 7
1(
#55826000
0(
#56097000
b100 7
1(
#56368000
0(
#56639000
b101 7
1(
#56910000
0(
#57181000
b110 7
1(
#57452000
0(
#57723000
b111 7
1(
#57994000
0(
#58265000
b1000 7
1(
#58536000
0(
#58807000
b1001 7
1(
#59078000
0(
#59349000
b1010 7
1(
#59620000
0(
#59891000
b1011 7
1(
#60162000
0(
#60433000
11
b0 7
1(
#60704000
0(
#60975000
b1 B
b1001 K
01
b1 7
1(
#61246000
0(
#61517000
b10 7
1(
#61788000
0(
#62059000
b11 7
1(
#62330000
0(
#62601000
b100 7
1(
#62872000
0(
#63143000
b101 7
1(
#63414000
0(
#63685000
b110 7
1(
#63956000
0(
#64227000
b111 7
1(
#64498000
0(
#64769000
b1000 7
1(
#65040000
0(
#65311000
b1001 7
1(
#65582000
0(
#65853000
b1010 7
1(
#66124000
0(
#66395000
b1011 7
1(
#66666000
0(
#66937000
11
b0 7
1(
#67208000
0(
#67479000
b10 B
b1010 K
01
b1 7
1(
#67750000
0(
#68021000
b10 7
1(
#68292000
0(
#68563000
b11 7
1(
#68834000
0(
#69105000
b100 7
1(
#69376000
0(
#69647000
b101 7
1(
#69918000
0(
#70189000
b110 7
1(
#70460000
0(
#70731000
b111 7
1(
#71002000
0(
#71273000
b1000 7
1(
#71544000
0(
#71815000
b1001 7
1(
#72086000
0(
#72357000
b1010 7
1(
#72628000
0(
#72899000
b1011 7
1(
#73170000
0(
#73441000
11
b0 7
1(
#73712000
0(
#73983000
b11 B
b1011 K
01
b1 7
1(
#74254000
0(
#74525000
b10 7
1(
#74796000
0(
#75067000
b11 7
1(
#75338000
0(
#75609000
b100 7
1(
#75880000
0(
#76151000
b101 7
1(
#76422000
0(
#76693000
b110 7
1(
#76964000
0(
#77235000
b111 7
1(
#77506000
0(
#77777000
b1000 7
1(
#78048000
0(
#78319000
b1001 7
1(
#78590000
0(
#78861000
b1010 7
1(
#79132000
0(
#79403000
b1011 7
1(
#79674000
0(
#79945000
11
b0 7
1(
#80216000
0(
#80487000
b100 B
b1100 K
01
b1 7
1(
#80758000
0(
#81029000
b10 7
1(
#81300000
0(
#81571000
b11 7
1(
#81842000
0(
#82113000
b100 7
1(
#82384000
0(
#82655000
b101 7
1(
#82926000
0(
#83197000
b110 7
1(
#83468000
0(
#83739000
b111 7
1(
#84010000
0(
#84281000
b1000 7
1(
#84552000
0(
#84823000
b1001 7
1(
#85094000
0(
#85365000
b1010 7
1(
#85636000
0(
#85907000
b1011 7
1(
#86178000
0(
#86449000
11
b0 7
1(
#86720000
0(
#86991000
b101 B
b1101 K
01
b1 7
1(
#87262000
0(
#87533000
b10 7
1(
#87804000
0(
#88075000
b11 7
1(
#88346000
0(
#88617000
b100 7
1(
#88888000
0(
#89159000
b101 7
1(
#89430000
0(
#89701000
b110 7
1(
#89972000
0(
#90243000
b111 7
1(
#90514000
0(
#90785000
b1000 7
1(
#91056000
0(
#91327000
b1001 7
1(
#91598000
0(
#91869000
b1010 7
1(
#92140000
0(
#92411000
b1011 7
1(
#92682000
0(
#92953000
11
b0 7
1(
#93224000
0(
#93495000
b110 B
b1110 K
01
b1 7
1(
#93766000
0(
#94037000
b10 7
1(
#94308000
0(
#94579000
b11 7
1(
#94850000
0(
#95121000
b100 7
1(
#95392000
0(
#95663000
b101 7
1(
#95934000
0(
#96205000
b110 7
1(
#96476000
0(
#96747000
b111 7
1(
#97018000
0(
#97289000
b1000 7
1(
#97560000
0(
#97831000
b1001 7
1(
#98102000
0(
#98373000
b1010 7
1(
#98644000
0(
#98915000
b1011 7
1(
#99186000
0(
#99457000
11
b0 7
1(
#99728000
0(
#99999000
b111 B
b1111 K
01
b1 7
1(
#100270000
0(
#100541000
b10 7
1(
#100812000
0(
#101083000
b11 7
1(
#101354000
0(
#101625000
b100 7
1(
#101896000
0(
#102167000
b101 7
1(
#102438000
0(
#102709000
b110 7
1(
#102980000
0(
#103251000
b111 7
1(
#103522000
0(
#103793000
b1000 7
1(
#104064000
0(
#104335000
b1001 7
1(
#104606000
0(
#104877000
b1010 7
1(
#105148000
0(
#105419000
b1011 7
1(
#105690000
0(
#105961000
11
b0 7
1(
#106232000
0(
#106503000
b1000 B
b10 J
b0 K
01
b1 7
1(
#106774000
0(
#107045000
b10 7
1"
1(
#107316000
0(
#107587000
1>
b11 7
1(
#107858000
0(
#108129000
b100 7
1?
1(
#108400000
0(
#108671000
b101 7
1(
#108942000
0(
#109213000
b110 7
1(
#109484000
0(
#109755000
b111 7
1(
#110026000
0(
#110297000
b1000 7
1(
#110568000
0(
#110839000
b1001 7
1(
#111110000
0(
#111381000
b1010 7
1(
#111652000
0(
#111923000
b1011 7
1(
#112194000
0(
#112465000
11
b0 7
1(
#112736000
0(
#113007000
b1001 B
b1 K
01
b1 7
1(
#113278000
0(
#113549000
b10 7
1(
#113820000
0(
#114091000
b11 7
1(
#114362000
0(
#114633000
b100 7
1(
#114904000
0(
#115175000
b101 7
1(
#115446000
0(
#115717000
b110 7
1(
#115988000
0(
#116259000
b111 7
1(
#116530000
0(
#116801000
b1000 7
1(
#117072000
0(
#117343000
b1001 7
1(
#117614000
0(
#117885000
b1010 7
1(
#118156000
0(
#118427000
b1011 7
1(
#118698000
0(
#118969000
11
b0 7
1(
#119240000
0(
#119511000
b1010 B
b10 K
01
b1 7
1(
#119782000
0(
#120053000
b10 7
1(
#120324000
0(
#120595000
b11 7
1(
#120866000
0(
#121137000
b100 7
1(
#121408000
0(
#121679000
b101 7
1(
#121950000
0(
#122221000
b110 7
1(
#122492000
0(
#122763000
b111 7
1(
#123034000
0(
#123305000
b1000 7
1(
#123576000
0(
#123847000
b1001 7
1(
#124118000
0(
#124389000
b1010 7
1(
#124660000
0(
#124931000
b1011 7
1(
#125202000
0(
#125473000
11
b0 7
1(
#125744000
0(
#126015000
b1011 B
b11 K
01
b1 7
1(
#126286000
0(
#126557000
b10 7
1(
#126828000
0(
#127099000
b11 7
1(
#127370000
0(
#127641000
b100 7
1(
#127912000
0(
#128183000
b101 7
1(
#128454000
0(
#128725000
b110 7
1(
#128996000
0(
#129267000
b111 7
1(
#129538000
0(
#129809000
b1000 7
1(
#130080000
0(
#130351000
b1001 7
1(
#130622000
0(
#130893000
b1010 7
1(
#131164000
0(
#131435000
b1011 7
1(
#131706000
0(
#131977000
11
b0 7
1(
#132248000
0(
#132519000
b1100 B
b100 K
01
b1 7
1(
#132790000
0(
#133061000
b10 7
1(
#133332000
0(
#133603000
b11 7
1(
#133874000
0(
#134145000
b100 7
1(
#134416000
0(
#134687000
b101 7
1(
#134958000
0(
#135229000
b110 7
1(
#135500000
0(
#135771000
b111 7
1(
#136042000
0(
#136313000
b1000 7
1(
#136584000
0(
#136855000
b1001 7
1(
#137126000
0(
#137397000
b1010 7
1(
#137668000
0(
#137939000
b1011 7
1(
#138210000
0(
#138481000
11
b0 7
1(
#138752000
0(
#139023000
b1101 B
b101 K
01
b1 7
1(
#139294000
0(
#139565000
b10 7
1(
#139836000
0(
#140107000
b11 7
1(
#140378000
0(
#140649000
b100 7
1(
#140920000
0(
#141191000
b101 7
1(
#141462000
0(
#141733000
b110 7
1(
#142004000
0(
#142275000
b111 7
1(
#142546000
0(
#142817000
b1000 7
1(
#143088000
0(
#143359000
b1001 7
1(
#143630000
0(
#143901000
b1010 7
1(
#144172000
0(
#144443000
b1011 7
1(
#144714000
0(
#144985000
11
b0 7
1(
#145256000
0(
#145527000
b1110 B
b110 K
01
b1 7
1(
#145798000
0(
#146069000
b10 7
1(
#146340000
0(
#146611000
b11 7
1(
#146882000
0(
#147153000
b100 7
1(
#147424000
0(
#147695000
b101 7
1(
#147966000
0(
#148237000
b110 7
1(
#148508000
0(
#148779000
b111 7
1(
#149050000
0(
#149321000
b1000 7
1(
#149592000
0(
#149863000
b1001 7
1(
#150134000
0(
#150405000
b1010 7
1(
#150676000
0(
#150947000
b1011 7
1(
#151218000
0(
#151489000
11
b0 7
1(
#151760000
0(
#152031000
b1111 B
b111 K
01
b1 7
1(
#152302000
0(
#152573000
b10 7
1(
#152844000
0(
#153115000
b11 7
1(
#153386000
0(
#153657000
b100 7
1(
#153928000
0(
#154199000
b101 7
1(
#154470000
0(
#154741000
b110 7
1(
#155012000
0(
#155283000
b111 7
1(
#155554000
0(
#155825000
b1000 7
1(
#156096000
0(
#156367000
b1001 7
1(
#156638000
0(
#156909000
b1010 7
1(
#157180000
0(
#157451000
b1011 7
1(
#157722000
0(
#157993000
11
b0 7
1(
#158264000
0(
#158535000
b1 <
b1 @
b0 B
b1000 K
01
b1 7
1(
#158806000
0(
#159077000
b10 7
1(
#159348000
0(
#159619000
b11 7
1(
